{
  "timestamp": "2021-06-22T00:00:00Z",
  "since": "daily",
  "language": "javascript",
  "total_count": 24,
  "new_repos_count": 0,
  "quality_score": 100,
  "source": "import:frodeaa/github_trending_archive",
  "quality_grade": "B",
  "import_batch_id": "batch-2026-01-22-094655",
  "repositories": [
    {
      "rank": 1,
      "owner": "trekhleb",
      "repo_name": "javascript-algorithms",
      "full_name": "trekhleb/javascript-algorithms",
      "url": "https://github.com/trekhleb/javascript-algorithms",
      "description": "📝 Algorithms and data structures implemented in JavaScript with explanations and links to further readings",
      "language": "JavaScript",
      "stars": 195413,
      "forks": 31119,
      "stars_today": 0,
      "is_new": false,
      "source": "import:frodeaa/github_trending_archive",
      "quality_grade": "B",
      "source_path": "/tmp/github_trending_archive/archive/2021-06/2021-06-22.md",
      "enrichment_status": "enriched",
      "enriched_at": "2026-01-24T03:29:23Z"
    },
    {
      "rank": 2,
      "owner": "algorithm-visualizer",
      "repo_name": "algorithm-visualizer",
      "full_name": "algorithm-visualizer/algorithm-visualizer",
      "url": "https://github.com/algorithm-visualizer/algorithm-visualizer",
      "description": ":fireworks:Interactive Online Platform that Visualizes Algorithms from Code",
      "language": "JavaScript",
      "stars": 48331,
      "forks": 7576,
      "stars_today": 0,
      "is_new": false,
      "source": "import:frodeaa/github_trending_archive",
      "quality_grade": "B",
      "source_path": "/tmp/github_trending_archive/archive/2021-06/2021-06-22.md",
      "enrichment_status": "enriched",
      "enriched_at": "2026-01-24T03:29:23Z"
    },
    {
      "rank": 3,
      "owner": "KarenOk",
      "repo_name": "whatsapp-web-clone",
      "full_name": "KarenOk/whatsapp-web-clone",
      "url": "https://github.com/KarenOk/whatsapp-web-clone",
      "description": "Clone of Whatsapp Web's current UI.",
      "language": "JavaScript",
      "stars": 735,
      "forks": 201,
      "stars_today": 0,
      "is_new": false,
      "source": "import:frodeaa/github_trending_archive",
      "quality_grade": "B",
      "source_path": "/tmp/github_trending_archive/archive/2021-06/2021-06-22.md",
      "enrichment_status": "enriched",
      "enriched_at": "2026-01-24T03:29:23Z"
    },
    {
      "rank": 4,
      "owner": "30-seconds",
      "repo_name": "30-seconds-of-code",
      "full_name": "30-seconds/30-seconds-of-code",
      "url": "https://github.com/30-seconds/30-seconds-of-code",
      "description": "Coding articles to level up your development skills",
      "language": "JavaScript",
      "stars": 126464,
      "forks": 12416,
      "stars_today": 0,
      "is_new": false,
      "source": "import:frodeaa/github_trending_archive",
      "quality_grade": "B",
      "source_path": "/tmp/github_trending_archive/archive/2021-06/2021-06-22.md",
      "enrichment_status": "enriched",
      "enriched_at": "2026-01-24T03:29:23Z"
    },
    {
      "rank": 5,
      "owner": "leonardomso",
      "repo_name": "33-js-concepts",
      "full_name": "leonardomso/33-js-concepts",
      "url": "https://github.com/leonardomso/33-js-concepts",
      "description": "📜 33 JavaScript concepts every developer should know.",
      "language": "JavaScript",
      "stars": 66176,
      "forks": 9193,
      "stars_today": 0,
      "is_new": false,
      "source": "import:frodeaa/github_trending_archive",
      "quality_grade": "B",
      "source_path": "/tmp/github_trending_archive/archive/2021-06/2021-06-22.md",
      "enrichment_status": "enriched",
      "enriched_at": "2026-01-24T03:29:23Z"
    },
    {
      "rank": 6,
      "owner": "WordPress",
      "repo_name": "gutenberg",
      "full_name": "WordPress/gutenberg",
      "url": "https://github.com/WordPress/gutenberg",
      "description": "The Block Editor project for WordPress and beyond. Plugin is available from the official repository.",
      "language": "JavaScript",
      "stars": 11532,
      "forks": 4691,
      "stars_today": 0,
      "is_new": false,
      "source": "import:frodeaa/github_trending_archive",
      "quality_grade": "B",
      "source_path": "/tmp/github_trending_archive/archive/2021-06/2021-06-22.md",
      "enrichment_status": "enriched",
      "enriched_at": "2026-01-24T03:29:23Z"
    },
    {
      "rank": 7,
      "owner": "goldbergyoni",
      "repo_name": "nodebestpractices",
      "full_name": "goldbergyoni/nodebestpractices",
      "url": "https://github.com/goldbergyoni/nodebestpractices",
      "description": ":white_check_mark:  The Node.js best practices list (July 2024)",
      "language": "Dockerfile",
      "stars": 104955,
      "forks": 10681,
      "stars_today": 0,
      "is_new": false,
      "source": "import:frodeaa/github_trending_archive",
      "quality_grade": "B",
      "source_path": "/tmp/github_trending_archive/archive/2021-06/2021-06-22.md",
      "enrichment_status": "enriched",
      "enriched_at": "2026-01-24T03:29:23Z"
    },
    {
      "rank": 8,
      "owner": "CesiumGS",
      "repo_name": "cesium",
      "full_name": "CesiumGS/cesium",
      "url": "https://github.com/CesiumGS/cesium",
      "description": "An open-source JavaScript library for world-class 3D globes and maps :earth_americas:",
      "language": "JavaScript",
      "stars": 14757,
      "forks": 3738,
      "stars_today": 0,
      "is_new": false,
      "source": "import:frodeaa/github_trending_archive",
      "quality_grade": "B",
      "source_path": "/tmp/github_trending_archive/archive/2021-06/2021-06-22.md",
      "enrichment_status": "enriched",
      "enriched_at": "2026-01-24T03:29:23Z"
    },
    {
      "rank": 9,
      "owner": "RocketChat",
      "repo_name": "Rocket.Chat",
      "full_name": "RocketChat/Rocket.Chat",
      "url": "https://github.com/RocketChat/Rocket.Chat",
      "description": "The Secure CommsOS™ for mission-critical operations",
      "language": "TypeScript",
      "stars": 44394,
      "forks": 13003,
      "stars_today": 0,
      "is_new": false,
      "source": "import:frodeaa/github_trending_archive",
      "quality_grade": "B",
      "source_path": "/tmp/github_trending_archive/archive/2021-06/2021-06-22.md",
      "enrichment_status": "enriched",
      "enriched_at": "2026-01-24T03:29:23Z"
    },
    {
      "rank": 10,
      "owner": "BlueWallet",
      "repo_name": "BlueWallet",
      "full_name": "BlueWallet/BlueWallet",
      "url": "https://github.com/BlueWallet/BlueWallet",
      "description": "Bitcoin wallet for iOS & Android. Built with React Native ",
      "language": "TypeScript",
      "stars": 3129,
      "forks": 986,
      "stars_today": 0,
      "is_new": false,
      "source": "import:frodeaa/github_trending_archive",
      "quality_grade": "B",
      "source_path": "/tmp/github_trending_archive/archive/2021-06/2021-06-22.md",
      "enrichment_status": "enriched",
      "enriched_at": "2026-01-24T03:29:23Z"
    },
    {
      "rank": 11,
      "owner": "iamadamdev",
      "repo_name": "bypass-paywalls-chrome",
      "full_name": "iamadamdev/bypass-paywalls-chrome",
      "url": "https://github.com/iamadamdev/bypass-paywalls-chrome",
      "description": "Bypass Paywalls web browser extension for Chrome and Firefox.",
      "language": "javascript",
      "stars": 0,
      "forks": 0,
      "stars_today": 0,
      "is_new": false,
      "source": "import:frodeaa/github_trending_archive",
      "quality_grade": "B",
      "source_path": "/tmp/github_trending_archive/archive/2021-06/2021-06-22.md"
    },
    {
      "rank": 12,
      "owner": "denysdovhan",
      "repo_name": "wtfjs",
      "full_name": "denysdovhan/wtfjs",
      "url": "https://github.com/denysdovhan/wtfjs",
      "description": "🤪 A list of funny and tricky JavaScript examples",
      "language": "JavaScript",
      "stars": 37609,
      "forks": 2670,
      "stars_today": 0,
      "is_new": false,
      "source": "import:frodeaa/github_trending_archive",
      "quality_grade": "B",
      "source_path": "/tmp/github_trending_archive/archive/2021-06/2021-06-22.md",
      "enrichment_status": "enriched",
      "enriched_at": "2026-01-24T03:29:23Z"
    },
    {
      "rank": 13,
      "owner": "yangshun",
      "repo_name": "front-end-interview-handbook",
      "full_name": "yangshun/front-end-interview-handbook",
      "url": "https://github.com/yangshun/front-end-interview-handbook",
      "description": "Front End interview preparation materials for busy engineers (updated for 2025)",
      "language": "MDX",
      "stars": 43821,
      "forks": 5948,
      "stars_today": 0,
      "is_new": false,
      "source": "import:frodeaa/github_trending_archive",
      "quality_grade": "B",
      "source_path": "/tmp/github_trending_archive/archive/2021-06/2021-06-22.md",
      "enrichment_status": "enriched",
      "enriched_at": "2026-01-24T03:29:23Z"
    },
    {
      "rank": 14,
      "owner": "quasarframework",
      "repo_name": "quasar",
      "full_name": "quasarframework/quasar",
      "url": "https://github.com/quasarframework/quasar",
      "description": "Quasar Framework - Build high-performance VueJS user interfaces in record time",
      "language": "JavaScript",
      "stars": 27045,
      "forks": 3681,
      "stars_today": 0,
      "is_new": false,
      "source": "import:frodeaa/github_trending_archive",
      "quality_grade": "B",
      "source_path": "/tmp/github_trending_archive/archive/2021-06/2021-06-22.md",
      "enrichment_status": "enriched",
      "enriched_at": "2026-01-24T03:29:23Z"
    },
    {
      "rank": 15,
      "owner": "nuxt",
      "repo_name": "nuxt.js",
      "full_name": "nuxt/nuxt.js",
      "url": "https://github.com/nuxt/nuxt.js",
      "description": "The Full-Stack Vue Framework.",
      "language": "TypeScript",
      "stars": 59413,
      "forks": 5504,
      "stars_today": 0,
      "is_new": false,
      "source": "import:frodeaa/github_trending_archive",
      "quality_grade": "B",
      "source_path": "/tmp/github_trending_archive/archive/2021-06/2021-06-22.md",
      "enrichment_status": "enriched",
      "enriched_at": "2026-01-24T03:29:23Z"
    },
    {
      "rank": 16,
      "owner": "modood",
      "repo_name": "Administrative-divisions-of-China",
      "full_name": "modood/Administrative-divisions-of-China",
      "url": "https://github.com/modood/Administrative-divisions-of-China",
      "description": "中华人民共和国行政区划：省级（省份）、 地级（城市）、 县级（区县）、 乡级（乡镇街道）、 村级（村委会居委会） ，中国省市区镇村二级三级四级五级联动地址数据。",
      "language": "JavaScript",
      "stars": 20491,
      "forks": 7231,
      "stars_today": 0,
      "is_new": false,
      "source": "import:frodeaa/github_trending_archive",
      "quality_grade": "B",
      "source_path": "/tmp/github_trending_archive/archive/2021-06/2021-06-22.md",
      "enrichment_status": "enriched",
      "enriched_at": "2026-01-24T03:29:23Z"
    },
    {
      "rank": 17,
      "owner": "grpc",
      "repo_name": "grpc-web",
      "full_name": "grpc/grpc-web",
      "url": "https://github.com/grpc/grpc-web",
      "description": "gRPC for Web Clients",
      "language": "JavaScript",
      "stars": 9167,
      "forks": 790,
      "stars_today": 0,
      "is_new": false,
      "source": "import:frodeaa/github_trending_archive",
      "quality_grade": "B",
      "source_path": "/tmp/github_trending_archive/archive/2021-06/2021-06-22.md",
      "enrichment_status": "enriched",
      "enriched_at": "2026-01-24T03:29:23Z"
    },
    {
      "rank": 18,
      "owner": "js-cookie",
      "repo_name": "js-cookie",
      "full_name": "js-cookie/js-cookie",
      "url": "https://github.com/js-cookie/js-cookie",
      "description": "A simple, lightweight JavaScript API for handling browser cookies",
      "language": "JavaScript",
      "stars": 22822,
      "forks": 2068,
      "stars_today": 0,
      "is_new": false,
      "source": "import:frodeaa/github_trending_archive",
      "quality_grade": "B",
      "source_path": "/tmp/github_trending_archive/archive/2021-06/2021-06-22.md",
      "enrichment_status": "enriched",
      "enriched_at": "2026-01-24T03:29:23Z"
    },
    {
      "rank": 19,
      "owner": "fengyuanchen",
      "repo_name": "viewerjs",
      "full_name": "fengyuanchen/viewerjs",
      "url": "https://github.com/fengyuanchen/viewerjs",
      "description": "JavaScript image viewer.",
      "language": "JavaScript",
      "stars": 8189,
      "forks": 1249,
      "stars_today": 0,
      "is_new": false,
      "source": "import:frodeaa/github_trending_archive",
      "quality_grade": "B",
      "source_path": "/tmp/github_trending_archive/archive/2021-06/2021-06-22.md",
      "enrichment_status": "enriched",
      "enriched_at": "2026-01-24T03:29:23Z"
    },
    {
      "rank": 20,
      "owner": "mrdoob",
      "repo_name": "three.js",
      "full_name": "mrdoob/three.js",
      "url": "https://github.com/mrdoob/three.js",
      "description": "JavaScript 3D Library.",
      "language": "JavaScript",
      "stars": 110509,
      "forks": 36242,
      "stars_today": 0,
      "is_new": false,
      "source": "import:frodeaa/github_trending_archive",
      "quality_grade": "B",
      "source_path": "/tmp/github_trending_archive/archive/2021-06/2021-06-22.md",
      "enrichment_status": "enriched",
      "enriched_at": "2026-01-24T03:29:23Z"
    },
    {
      "rank": 21,
      "owner": "JDHelloWorld",
      "repo_name": "jd_scripts",
      "full_name": "JDHelloWorld/jd_scripts",
      "url": "https://github.com/JDHelloWorld/jd_scripts",
      "description": "* [https://github.com/facebook/react-native](facebook/react-native) A framework for building native apps with React.",
      "language": "JavaScript",
      "stars": 2261,
      "forks": 989,
      "stars_today": 0,
      "is_new": false,
      "source": "import:frodeaa/github_trending_archive",
      "quality_grade": "B",
      "source_path": "/tmp/github_trending_archive/archive/2021-06/2021-06-22.md",
      "enrichment_status": "enriched",
      "enriched_at": "2026-01-24T03:29:23Z"
    },
    {
      "rank": 22,
      "owner": "facebook",
      "repo_name": "react",
      "full_name": "facebook/react",
      "url": "https://github.com/facebook/react",
      "description": "The library for web and native user interfaces.",
      "language": "JavaScript",
      "stars": 242462,
      "forks": 50449,
      "stars_today": 0,
      "is_new": false,
      "source": "import:frodeaa/github_trending_archive",
      "quality_grade": "B",
      "source_path": "/tmp/github_trending_archive/archive/2021-06/2021-06-22.md",
      "enrichment_status": "enriched",
      "enriched_at": "2026-01-24T03:29:23Z"
    },
    {
      "rank": 23,
      "owner": "wix",
      "repo_name": "Detox",
      "full_name": "wix/Detox",
      "url": "https://github.com/wix/Detox",
      "description": "Gray box end-to-end testing and automation framework for mobile apps",
      "language": "JavaScript",
      "stars": 11782,
      "forks": 1919,
      "stars_today": 0,
      "is_new": false,
      "source": "import:frodeaa/github_trending_archive",
      "quality_grade": "B",
      "source_path": "/tmp/github_trending_archive/archive/2021-06/2021-06-22.md",
      "enrichment_status": "enriched",
      "enriched_at": "2026-01-24T03:29:23Z"
    },
    {
      "rank": 24,
      "owner": "gatsbyjs",
      "repo_name": "gatsby",
      "full_name": "gatsbyjs/gatsby",
      "url": "https://github.com/gatsbyjs/gatsby",
      "description": "The best React-based framework with performance, scalability and security built in.",
      "language": "JavaScript",
      "stars": 55973,
      "forks": 10251,
      "stars_today": 0,
      "is_new": false,
      "source": "import:frodeaa/github_trending_archive",
      "quality_grade": "B",
      "source_path": "/tmp/github_trending_archive/archive/2021-06/2021-06-22.md",
      "enrichment_status": "enriched",
      "enriched_at": "2026-01-24T03:29:23Z"
    }
  ]
}
