{
  "timestamp": "2018-07-13T00:00:00Z",
  "since": "daily",
  "language": "go",
  "total_count": 24,
  "new_repos_count": 0,
  "quality_score": 100,
  "source": "import:frodeaa/github_trending_archive",
  "quality_grade": "B",
  "import_batch_id": "batch-2026-01-22-100657",
  "repositories": [
    {
      "rank": 1,
      "owner": "https:",
      "repo_name": "/github.com/gaia-pipeline/gaia",
      "full_name": "https://github.com/gaia-pipeline/gaia",
      "url": "https://github.com/https://github.com/gaia-pipeline/gaia",
      "description": "Build powerful pipelines in any programming language.",
      "language": "go",
      "stars": 0,
      "forks": 0,
      "stars_today": 0,
      "is_new": false,
      "source": "import:frodeaa/github_trending_archive",
      "quality_grade": "B",
      "source_path": "/tmp/github_trending_archive/archive/2018-07/2018-07-13.md"
    },
    {
      "rank": 2,
      "owner": "https:",
      "repo_name": "/github.com/cosmos72/gomacro",
      "full_name": "https://github.com/cosmos72/gomacro",
      "url": "https://github.com/https://github.com/cosmos72/gomacro",
      "description": "Interactive Go interpreter and debugger with REPL, Eval, generics and Lisp-like macros",
      "language": "go",
      "stars": 0,
      "forks": 0,
      "stars_today": 0,
      "is_new": false,
      "source": "import:frodeaa/github_trending_archive",
      "quality_grade": "B",
      "source_path": "/tmp/github_trending_archive/archive/2018-07/2018-07-13.md"
    },
    {
      "rank": 3,
      "owner": "https:",
      "repo_name": "/github.com/perlin-network/noise",
      "full_name": "https://github.com/perlin-network/noise",
      "url": "https://github.com/https://github.com/perlin-network/noise",
      "description": "A decentralized P2P networking stack written in Go.",
      "language": "go",
      "stars": 0,
      "forks": 0,
      "stars_today": 0,
      "is_new": false,
      "source": "import:frodeaa/github_trending_archive",
      "quality_grade": "B",
      "source_path": "/tmp/github_trending_archive/archive/2018-07/2018-07-13.md"
    },
    {
      "rank": 4,
      "owner": "https:",
      "repo_name": "/github.com/josephyzhou/github-trending",
      "full_name": "https://github.com/josephyzhou/github-trending",
      "url": "https://github.com/https://github.com/josephyzhou/github-trending",
      "description": "Tracking the most popular Github repos, updated daily",
      "language": "go",
      "stars": 0,
      "forks": 0,
      "stars_today": 0,
      "is_new": false,
      "source": "import:frodeaa/github_trending_archive",
      "quality_grade": "B",
      "source_path": "/tmp/github_trending_archive/archive/2018-07/2018-07-13.md"
    },
    {
      "rank": 5,
      "owner": "https:",
      "repo_name": "/github.com/FiloSottile/mkcert",
      "full_name": "https://github.com/FiloSottile/mkcert",
      "url": "https://github.com/https://github.com/FiloSottile/mkcert",
      "description": "A simple zero-config tool to make locally trusted development certificates with any names you'd like.",
      "language": "go",
      "stars": 0,
      "forks": 0,
      "stars_today": 0,
      "is_new": false,
      "source": "import:frodeaa/github_trending_archive",
      "quality_grade": "B",
      "source_path": "/tmp/github_trending_archive/archive/2018-07/2018-07-13.md"
    },
    {
      "rank": 6,
      "owner": "https:",
      "repo_name": "/github.com/ory/oathkeeper",
      "full_name": "https://github.com/ory/oathkeeper",
      "url": "https://github.com/https://github.com/ory/oathkeeper",
      "description": "A cloud native Identity &amp; Access Proxy (IAP) which authenticates and authorizes incoming HTTP requests. Inspired by the BeyondCorp / Zero Trust white paper. Written in Go.",
      "language": "go",
      "stars": 0,
      "forks": 0,
      "stars_today": 0,
      "is_new": false,
      "source": "import:frodeaa/github_trending_archive",
      "quality_grade": "B",
      "source_path": "/tmp/github_trending_archive/archive/2018-07/2018-07-13.md"
    },
    {
      "rank": 7,
      "owner": "https:",
      "repo_name": "/github.com/kubernetes/kubernetes",
      "full_name": "https://github.com/kubernetes/kubernetes",
      "url": "https://github.com/https://github.com/kubernetes/kubernetes",
      "description": "Production-Grade Container Scheduling and Management",
      "language": "go",
      "stars": 0,
      "forks": 0,
      "stars_today": 0,
      "is_new": false,
      "source": "import:frodeaa/github_trending_archive",
      "quality_grade": "B",
      "source_path": "/tmp/github_trending_archive/archive/2018-07/2018-07-13.md"
    },
    {
      "rank": 8,
      "owner": "https:",
      "repo_name": "/github.com/integrii/flaggy",
      "full_name": "https://github.com/integrii/flaggy",
      "url": "https://github.com/https://github.com/integrii/flaggy",
      "description": "Idiomatic Go input parsing with subcommands, positional values, and flags at any position. No required project or package layout and no external dependencies.",
      "language": "go",
      "stars": 0,
      "forks": 0,
      "stars_today": 0,
      "is_new": false,
      "source": "import:frodeaa/github_trending_archive",
      "quality_grade": "B",
      "source_path": "/tmp/github_trending_archive/archive/2018-07/2018-07-13.md"
    },
    {
      "rank": 9,
      "owner": "https:",
      "repo_name": "/github.com/golang/go",
      "full_name": "https://github.com/golang/go",
      "url": "https://github.com/https://github.com/golang/go",
      "description": "The Go programming language",
      "language": "go",
      "stars": 0,
      "forks": 0,
      "stars_today": 0,
      "is_new": false,
      "source": "import:frodeaa/github_trending_archive",
      "quality_grade": "B",
      "source_path": "/tmp/github_trending_archive/archive/2018-07/2018-07-13.md"
    },
    {
      "rank": 10,
      "owner": "https:",
      "repo_name": "/github.com/didi/falcon-log-agent",
      "full_name": "https://github.com/didi/falcon-log-agent",
      "url": "https://github.com/https://github.com/didi/falcon-log-agent",
      "description": "用于监控系统的日志采集agent，可无缝对接open-falcon",
      "language": "go",
      "stars": 0,
      "forks": 0,
      "stars_today": 0,
      "is_new": false,
      "source": "import:frodeaa/github_trending_archive",
      "quality_grade": "B",
      "source_path": "/tmp/github_trending_archive/archive/2018-07/2018-07-13.md"
    },
    {
      "rank": 11,
      "owner": "https:",
      "repo_name": "/github.com/usefathom/fathom",
      "full_name": "https://github.com/usefathom/fathom",
      "url": "https://github.com/https://github.com/usefathom/fathom",
      "description": "Fathom. Simple, trustworthy website analytics. Built with Golang &amp; Preact.",
      "language": "go",
      "stars": 0,
      "forks": 0,
      "stars_today": 0,
      "is_new": false,
      "source": "import:frodeaa/github_trending_archive",
      "quality_grade": "B",
      "source_path": "/tmp/github_trending_archive/archive/2018-07/2018-07-13.md"
    },
    {
      "rank": 12,
      "owner": "https:",
      "repo_name": "/github.com/gotoz/runq",
      "full_name": "https://github.com/gotoz/runq",
      "url": "https://github.com/https://github.com/gotoz/runq",
      "description": "run regular Docker images in KVM/Qemu",
      "language": "go",
      "stars": 0,
      "forks": 0,
      "stars_today": 0,
      "is_new": false,
      "source": "import:frodeaa/github_trending_archive",
      "quality_grade": "B",
      "source_path": "/tmp/github_trending_archive/archive/2018-07/2018-07-13.md"
    },
    {
      "rank": 13,
      "owner": "https:",
      "repo_name": "/github.com/alipay/sofa-mosn",
      "full_name": "https://github.com/alipay/sofa-mosn",
      "url": "https://github.com/https://github.com/alipay/sofa-mosn",
      "description": "* [https://github.com/avelino/awesome-go](avelino/awesome-go) A curated list of awesome Go frameworks, libraries and software",
      "language": "go",
      "stars": 0,
      "forks": 0,
      "stars_today": 0,
      "is_new": false,
      "source": "import:frodeaa/github_trending_archive",
      "quality_grade": "B",
      "source_path": "/tmp/github_trending_archive/archive/2018-07/2018-07-13.md"
    },
    {
      "rank": 14,
      "owner": "https:",
      "repo_name": "/github.com/hazbo/httpu",
      "full_name": "https://github.com/hazbo/httpu",
      "url": "https://github.com/https://github.com/hazbo/httpu",
      "description": "The terminal-first http client",
      "language": "go",
      "stars": 0,
      "forks": 0,
      "stars_today": 0,
      "is_new": false,
      "source": "import:frodeaa/github_trending_archive",
      "quality_grade": "B",
      "source_path": "/tmp/github_trending_archive/archive/2018-07/2018-07-13.md"
    },
    {
      "rank": 15,
      "owner": "https:",
      "repo_name": "/github.com/istio/istio",
      "full_name": "https://github.com/istio/istio",
      "url": "https://github.com/https://github.com/istio/istio",
      "description": "An open platform to connect, manage, and secure microservices.",
      "language": "go",
      "stars": 0,
      "forks": 0,
      "stars_today": 0,
      "is_new": false,
      "source": "import:frodeaa/github_trending_archive",
      "quality_grade": "B",
      "source_path": "/tmp/github_trending_archive/archive/2018-07/2018-07-13.md"
    },
    {
      "rank": 16,
      "owner": "https:",
      "repo_name": "/github.com/ethereum/go-ethereum",
      "full_name": "https://github.com/ethereum/go-ethereum",
      "url": "https://github.com/https://github.com/ethereum/go-ethereum",
      "description": "Official Go implementation of the Ethereum protocol",
      "language": "go",
      "stars": 0,
      "forks": 0,
      "stars_today": 0,
      "is_new": false,
      "source": "import:frodeaa/github_trending_archive",
      "quality_grade": "B",
      "source_path": "/tmp/github_trending_archive/archive/2018-07/2018-07-13.md"
    },
    {
      "rank": 17,
      "owner": "https:",
      "repo_name": "/github.com/prometheus/prometheus",
      "full_name": "https://github.com/prometheus/prometheus",
      "url": "https://github.com/https://github.com/prometheus/prometheus",
      "description": "The Prometheus monitoring system and time series database.",
      "language": "go",
      "stars": 0,
      "forks": 0,
      "stars_today": 0,
      "is_new": false,
      "source": "import:frodeaa/github_trending_archive",
      "quality_grade": "B",
      "source_path": "/tmp/github_trending_archive/archive/2018-07/2018-07-13.md"
    },
    {
      "rank": 18,
      "owner": "https:",
      "repo_name": "/github.com/gogs/gogs",
      "full_name": "https://github.com/gogs/gogs",
      "url": "https://github.com/https://github.com/gogs/gogs",
      "description": "Gogs is a painless self-hosted Git service.",
      "language": "go",
      "stars": 0,
      "forks": 0,
      "stars_today": 0,
      "is_new": false,
      "source": "import:frodeaa/github_trending_archive",
      "quality_grade": "B",
      "source_path": "/tmp/github_trending_archive/archive/2018-07/2018-07-13.md"
    },
    {
      "rank": 19,
      "owner": "https:",
      "repo_name": "/github.com/astaxie/build-web-application-with-golang",
      "full_name": "https://github.com/astaxie/build-web-application-with-golang",
      "url": "https://github.com/https://github.com/astaxie/build-web-application-with-golang",
      "description": "A golang ebook intro how to build a web with golang",
      "language": "go",
      "stars": 0,
      "forks": 0,
      "stars_today": 0,
      "is_new": false,
      "source": "import:frodeaa/github_trending_archive",
      "quality_grade": "B",
      "source_path": "/tmp/github_trending_archive/archive/2018-07/2018-07-13.md"
    },
    {
      "rank": 20,
      "owner": "https:",
      "repo_name": "/github.com/iikira/BaiduPCS-Go",
      "full_name": "https://github.com/iikira/BaiduPCS-Go",
      "url": "https://github.com/https://github.com/iikira/BaiduPCS-Go",
      "description": "百度网盘客户端 - Go语言编写",
      "language": "go",
      "stars": 0,
      "forks": 0,
      "stars_today": 0,
      "is_new": false,
      "source": "import:frodeaa/github_trending_archive",
      "quality_grade": "B",
      "source_path": "/tmp/github_trending_archive/archive/2018-07/2018-07-13.md"
    },
    {
      "rank": 21,
      "owner": "https:",
      "repo_name": "/github.com/gohugoio/hugo",
      "full_name": "https://github.com/gohugoio/hugo",
      "url": "https://github.com/https://github.com/gohugoio/hugo",
      "description": "The world’s fastest framework for building websites.",
      "language": "go",
      "stars": 0,
      "forks": 0,
      "stars_today": 0,
      "is_new": false,
      "source": "import:frodeaa/github_trending_archive",
      "quality_grade": "B",
      "source_path": "/tmp/github_trending_archive/archive/2018-07/2018-07-13.md"
    },
    {
      "rank": 22,
      "owner": "https:",
      "repo_name": "/github.com/fatedier/frp",
      "full_name": "https://github.com/fatedier/frp",
      "url": "https://github.com/https://github.com/fatedier/frp",
      "description": "A fast reverse proxy to help you expose a local server behind a NAT or firewall to the internet.",
      "language": "go",
      "stars": 0,
      "forks": 0,
      "stars_today": 0,
      "is_new": false,
      "source": "import:frodeaa/github_trending_archive",
      "quality_grade": "B",
      "source_path": "/tmp/github_trending_archive/archive/2018-07/2018-07-13.md"
    },
    {
      "rank": 23,
      "owner": "https:",
      "repo_name": "/github.com/oklog/ulid",
      "full_name": "https://github.com/oklog/ulid",
      "url": "https://github.com/https://github.com/oklog/ulid",
      "description": "Universally Unique Lexicographically Sortable Identifier (ULID) in Go",
      "language": "go",
      "stars": 0,
      "forks": 0,
      "stars_today": 0,
      "is_new": false,
      "source": "import:frodeaa/github_trending_archive",
      "quality_grade": "B",
      "source_path": "/tmp/github_trending_archive/archive/2018-07/2018-07-13.md"
    },
    {
      "rank": 24,
      "owner": "https:",
      "repo_name": "/github.com/junegunn/fzf",
      "full_name": "https://github.com/junegunn/fzf",
      "url": "https://github.com/https://github.com/junegunn/fzf",
      "description": "🌸A command-line fuzzy finder",
      "language": "go",
      "stars": 0,
      "forks": 0,
      "stars_today": 0,
      "is_new": false,
      "source": "import:frodeaa/github_trending_archive",
      "quality_grade": "B",
      "source_path": "/tmp/github_trending_archive/archive/2018-07/2018-07-13.md"
    }
  ]
}